wger/__init__.py
wger/__main__.py
wger/i18n.tpl
wger/settings.tpl
wger/settings_global.py
wger/tasks.py
wger/urls.py
wger/wsgi.py
wger/config/__init__.py
wger/config/apps.py
wger/config/signals.py
wger/config/urls.py
wger/config/fixtures/gym_config.json
wger/config/fixtures/language_config.json
wger/config/fixtures/test-languages.json
wger/config/migrations/0001_initial.py
wger/config/migrations/0002_auto_20190618_1617.py
wger/config/migrations/__init__.py
wger/config/models/__init__.py
wger/config/models/gym_config.py
wger/config/models/language_config.py
wger/config/templates/language/overview.html
wger/config/templates/language/view.html
wger/config/tests/__init__.py
wger/config/tests/test_custom_header.py
wger/config/tests/test_gym_config.py
wger/config/tests/test_language_config.py
wger/config/views/__init__.py
wger/config/views/gym_config.py
wger/config/views/language_config.py
wger/core/__init__.py
wger/core/apps.py
wger/core/demo.py
wger/core/forms.py
wger/core/signals.py
wger/core/urls.py
wger/core/api/__init__.py
wger/core/api/permissions.py
wger/core/api/resources.py
wger/core/api/serializers.py
wger/core/api/views.py
wger/core/fixtures/days_of_week.json
wger/core/fixtures/groups.json
wger/core/fixtures/languages.json
wger/core/fixtures/licenses.json
wger/core/fixtures/setting_repetition_units.json
wger/core/fixtures/setting_weight_units.json
wger/core/fixtures/test-licenses.json
wger/core/fixtures/test-user-data.README
wger/core/fixtures/test-user-data.json
wger/core/fixtures/users.json
wger/core/management/__init__.py
wger/core/management/commands/__init__.py
wger/core/management/commands/add-user-rest.py
wger/core/management/commands/clear-cache.py
wger/core/management/commands/delete-temp-users.py
wger/core/management/commands/extract-i18n.py
wger/core/management/commands/list-users-api.py
wger/core/management/commands/set-site-url.py
wger/core/management/commands/update-user-cache.py
wger/core/migrations/0001_initial.py
wger-2.1.dist-info/AUTHORS.rst
wger-2.1.dist-info/LICENSE.txt
wger-2.1.dist-info/METADATA
wger-2.1.dist-info/WHEEL
wger-2.1.dist-info/entry_points.txt
wger-2.1.dist-info/top_level.txt
wger-2.1.dist-info/RECORD
