Metadata-Version: 2.1
Name: wger
Version: 2.1
Summary: FLOSS workout, fitness and weight manager/tracker written with Django
Home-page: https://github.com/wger-project
Author: Roland Geider
Author-email: roland@geider.net
License: AGPL3+
Classifier: Development Status :: 5 - Production/Stable
Classifier: Environment :: Web Environment
Classifier: Intended Audience :: Other Audience
Classifier: Framework :: Django
Classifier: License :: OSI Approved :: GNU Affero General Public License v3 or later (AGPLv3+)
Classifier: Operating System :: OS Independent
Classifier: Programming Language :: Python :: 3
Classifier: Programming Language :: Python :: 3.8
Classifier: Programming Language :: Python :: 3.9
Classifier: Programming Language :: Python :: 3.10
License-File: LICENSE.txt
License-File: AUTHORS.rst
Requires-Dist: bleach[css] (~=5.0)
Requires-Dist: django-bootstrap-breadcrumbs (~=0.9)
Requires-Dist: django-formtools (~=2.4)
Requires-Dist: django-recaptcha (~=3.0.0)
Requires-Dist: Django (~=3.2)
Requires-Dist: django-activity-stream (~=1.4)
Requires-Dist: django-crispy-forms (~=1.14)
Requires-Dist: django-simple-history (~=3.1)
Requires-Dist: django-email-verification (~=0.1.0)
Requires-Dist: django-compressor (~=4.1)
Requires-Dist: django-extensions (~=3.2)
Requires-Dist: django-storages (~=1.13)
Requires-Dist: django-environ (==0.9.0)
Requires-Dist: easy-thumbnails (==2.8.3)
Requires-Dist: fontawesomefree (~=6.1.1)
Requires-Dist: icalendar (==4.1.0)
Requires-Dist: invoke (==1.7.3)
Requires-Dist: pillow (==9.2.0)
Requires-Dist: reportlab (==3.6.11)
Requires-Dist: requests (==2.28.1)
Requires-Dist: django-cors-headers (==3.13.0)
Requires-Dist: django-filter (==22.1)
Requires-Dist: djangorestframework (~=3.14)
Requires-Dist: django-sortedm2m (~=3.1)
